[
    {
        "userId": 1,
        "fileId": 2,
        "fileSize": "27MB",
        "vidioTitle": "tom",
        "videoName": "Tom and Jerry 11.mp4",
        "data": "2022-01-05 | 06:53",
        "vidioUrl": "/data/files/Tom and Jerry 11.mp4"
    },
    {
        "userId": 1,
        "fileSize": "24MB",
        "fileId": 5,
        "vidioTitle": "Tom Jery",
        "data": "2022-01-05  16:13",
        "videoName": "TomandJerry11.mp4",
        "vidioUrl": "/data/files/TomandJerry11.mp4"
    },
    {
        "userId": 4,
        "fileSize": "26MB",
        "fileId": 6,
        "vidioTitle": "Tomi jery",
        "data": "2022-01-05 | 17:53",
        "videoName": "TomandJerry12-BabyPuss(1943).mp4",
        "vidioUrl": "/data/files/TomandJerry12-BabyPuss(1943).mp4"
    },
    {
        "userId": 4,
        "fileSize": "16MB",
        "fileId": 7,
        "vidioTitle": "Vidio",
        "data": "2022-01-05 | 18:33",
        "videoName": "2021-12-0820-02-34.mp4",
        "vidioUrl": "/data/files/2021-12-0820-02-34.mp4"
    }
]